unicodedataplus.cpython-39-i386-linux-gnu.so
unicodedataplus-16.0.0.post1.dist-info/LICENSE
unicodedataplus-16.0.0.post1.dist-info/WHEEL
unicodedataplus-16.0.0.post1.dist-info/RECORD
unicodedataplus-16.0.0.post1.dist-info/top_level.txt
unicodedataplus-16.0.0.post1.dist-info/METADATA
