Metadata-Version: 2.1
Name: unicodedataplus
Version: 16.0.0.post1
Summary: Unicodedata with extensions for additional properties.
Home-page: http://github.com/iwsfutcmd/unicodedataplus
Download-URL: http://github.com/iwsfutcmd/unicodedataplus
Author: Ben Joeng (Yang)
Author-email: benayang@gmail.com
License: Apache License 2.0
Platform: any
License-File: LICENSE
